django_mcp/__init__.py
django_mcp/admin_tools.py
django_mcp/api.py
django_mcp/api_inspection.py
django_mcp/apps.py
django_mcp/asgi.py
django_mcp/context.py
django_mcp/decorators.py
django_mcp/drf_tools.py
django_mcp/inspection.py
django_mcp/model_tools.py
django_mcp/server.py
django_mcp/settings.py
django_mcp/urls.py
django_mcp/views.py
django_mcp/management/__init__.py
django_mcp/management/commands/__init__.py
django_mcp/management/commands/mcp_inspect.py
django_mcp/management/commands/mcp_serve.py
django_mcp/management/commands/mcp_test.py
django_mcp/templates/django_mcp/dashboard.html
iflow_mcp_hyperb1iss_django_mcp-0.1.0.dist-info/METADATA
iflow_mcp_hyperb1iss_django_mcp-0.1.0.dist-info/WHEEL
iflow_mcp_hyperb1iss_django_mcp-0.1.0.dist-info/entry_points.txt
iflow_mcp_hyperb1iss_django_mcp-0.1.0.dist-info/licenses/LICENSE
iflow_mcp_hyperb1iss_django_mcp-0.1.0.dist-info/RECORD
