Metadata-Version: 2.4
Name: iflow-mcp_hyperb1iss_django-mcp
Version: 0.1.0
Summary: Integrate Model Context Protocol with Django
Project-URL: Homepage, https://github.com/hyperbliss/django-mcp
Project-URL: Issues, https://github.com/hyperbliss/django-mcp/issues
Project-URL: Documentation, https://github.com/hyperbliss/django-mcp#readme
Author-email: Stefanie Jane <stef@hyperbliss.tech>
License:                                  Apache License
License-File: LICENSE
Keywords: ai,claude,django,llm,mcp
Classifier: Development Status :: 4 - Beta
Classifier: Intended Audience :: Developers
Classifier: License :: OSI Approved :: Apache Software License
Classifier: Programming Language :: Python :: 3
Classifier: Programming Language :: Python :: 3.11
Classifier: Programming Language :: Python :: 3.12
Classifier: Programming Language :: Python :: 3.13
Requires-Python: >=3.11
Requires-Dist: django>=5.1.7
Requires-Dist: djangorestframework>=3.15.2
Requires-Dist: httpx>=0.28.1
Requires-Dist: mcp[cli]>=1.4.1
Requires-Dist: rich>=13.9.4
Requires-Dist: sse-starlette>=2.2.1
Requires-Dist: starlette>=0.46.0
Requires-Dist: uvicorn>=0.34.0
